fyle_rest_auth/__init__.py
fyle_rest_auth/admin.py
fyle_rest_auth/apps.py
fyle_rest_auth/authentication.py
fyle_rest_auth/helpers.py
fyle_rest_auth/models.py
fyle_rest_auth/urls.py
fyle_rest_auth/utils.py
fyle_rest_auth/views.py
fyle_rest_auth/migrations/0001_initial.py
fyle_rest_auth/migrations/0002_auto_20200101_1205.py
fyle_rest_auth/migrations/0003_auto_20200107_0921.py
fyle_rest_auth/migrations/0004_auto_20200107_1345.py
fyle_rest_auth/migrations/0005_remove_authtoken_access_token.py
fyle_rest_auth/migrations/0006_auto_20201221_0849.py
fyle_rest_auth/migrations/__init__.py
fyle_rest_auth-1.8.3.dist-info/licenses/LICENSE
fyle_rest_auth-1.8.3.dist-info/METADATA
fyle_rest_auth-1.8.3.dist-info/WHEEL
fyle_rest_auth-1.8.3.dist-info/top_level.txt
fyle_rest_auth-1.8.3.dist-info/RECORD
