Metadata-Version: 2.4
Name: fyle-rest-auth
Version: 1.8.3
Summary: Django application to implement OAuth 2.0 using Fyle in Django rest framework
Home-page: https://github.com/fylein/fyle-rest-auth
Author: Shwetabh Kumar
Author-email: shwetabh.kumar@fyle.in
License: MIT
Keywords: fyle,rest,django-rest-framework,api,python,oauth 2
Classifier: Framework :: Django
Classifier: Intended Audience :: Developers
Classifier: Intended Audience :: System Administrators
Classifier: Operating System :: OS Independent
Classifier: Topic :: Software Development
License-File: LICENSE
Requires-Dist: requests>=2.25.0
Requires-Dist: django>=3.0.2
Requires-Dist: django-rest-framework==0.1.0
Dynamic: author
Dynamic: author-email
Dynamic: classifier
Dynamic: description
Dynamic: description-content-type
Dynamic: home-page
Dynamic: keywords
Dynamic: license
Dynamic: license-file
Dynamic: requires-dist
Dynamic: summary
